<annotation>
	<folder>data_images</folder>
	<filename>battery11.jpg</filename>
	<path>/Users/yewinthant/Desktop/Imp_Honos_Project/YOLO_Waste_Det_And_Cls_Project/Notes/datapreparation/data_images/battery11.jpg</path>
	<source>
		<database>Unknown</database>
	</source>
	<size>
		<width>224</width>
		<height>224</height>
		<depth>3</depth>
	</size>
	<segmented>0</segmented>
	<object>
		<name>battery</name>
		<pose>Unspecified</pose>
		<truncated>0</truncated>
		<difficult>0</difficult>
		<bndbox>
			<xmin>6</xmin>
			<ymin>29</ymin>
			<xmax>62</xmax>
			<ymax>201</ymax>
		</bndbox>
	</object>
	<object>
		<name>battery</name>
		<pose>Unspecified</pose>
		<truncated>0</truncated>
		<difficult>0</difficult>
		<bndbox>
			<xmin>59</xmin>
			<ymin>30</ymin>
			<xmax>114</xmax>
			<ymax>202</ymax>
		</bndbox>
	</object>
	<object>
		<name>battery</name>
		<pose>Unspecified</pose>
		<truncated>0</truncated>
		<difficult>0</difficult>
		<bndbox>
			<xmin>113</xmin>
			<ymin>30</ymin>
			<xmax>167</xmax>
			<ymax>202</ymax>
		</bndbox>
	</object>
	<object>
		<name>battery</name>
		<pose>Unspecified</pose>
		<truncated>0</truncated>
		<difficult>0</difficult>
		<bndbox>
			<xmin>164</xmin>
			<ymin>30</ymin>
			<xmax>219</xmax>
			<ymax>203</ymax>
		</bndbox>
	</object>
</annotation>
