<annotation>
	<folder>data_images</folder>
	<filename>biological658.jpg</filename>
	<path>/Users/yewinthant/Desktop/Imp_Honos_Project/YOLO_Waste_Det_And_Cls_Project/Notes/datapreparation/data_images/biological658.jpg</path>
	<source>
		<database>Unknown</database>
	</source>
	<size>
		<width>269</width>
		<height>188</height>
		<depth>3</depth>
	</size>
	<segmented>0</segmented>
	<object>
		<name>biological</name>
		<pose>Unspecified</pose>
		<truncated>0</truncated>
		<difficult>0</difficult>
		<bndbox>
			<xmin>7</xmin>
			<ymin>39</ymin>
			<xmax>138</xmax>
			<ymax>151</ymax>
		</bndbox>
	</object>
	<object>
		<name>biological</name>
		<pose>Unspecified</pose>
		<truncated>0</truncated>
		<difficult>0</difficult>
		<bndbox>
			<xmin>123</xmin>
			<ymin>100</ymin>
			<xmax>182</xmax>
			<ymax>154</ymax>
		</bndbox>
	</object>
	<object>
		<name>biological</name>
		<pose>Unspecified</pose>
		<truncated>1</truncated>
		<difficult>0</difficult>
		<bndbox>
			<xmin>128</xmin>
			<ymin>1</ymin>
			<xmax>257</xmax>
			<ymax>119</ymax>
		</bndbox>
	</object>
</annotation>
