<annotation>
	<folder>data_images</folder>
	<filename>plastic574.jpg</filename>
	<path>/Users/yewinthant/Desktop/Imp_Honos_Project/YOLO_Waste_Det_And_Cls_Project/Notes/datapreparation/data_images/plastic574.jpg</path>
	<source>
		<database>Unknown</database>
	</source>
	<size>
		<width>258</width>
		<height>195</height>
		<depth>3</depth>
	</size>
	<segmented>0</segmented>
	<object>
		<name>plastic</name>
		<pose>Unspecified</pose>
		<truncated>1</truncated>
		<difficult>0</difficult>
		<bndbox>
			<xmin>15</xmin>
			<ymin>1</ymin>
			<xmax>74</xmax>
			<ymax>179</ymax>
		</bndbox>
	</object>
	<object>
		<name>plastic</name>
		<pose>Unspecified</pose>
		<truncated>0</truncated>
		<difficult>0</difficult>
		<bndbox>
			<xmin>74</xmin>
			<ymin>3</ymin>
			<xmax>130</xmax>
			<ymax>180</ymax>
		</bndbox>
	</object>
	<object>
		<name>plastic</name>
		<pose>Unspecified</pose>
		<truncated>0</truncated>
		<difficult>0</difficult>
		<bndbox>
			<xmin>131</xmin>
			<ymin>3</ymin>
			<xmax>188</xmax>
			<ymax>180</ymax>
		</bndbox>
	</object>
	<object>
		<name>plastic</name>
		<pose>Unspecified</pose>
		<truncated>0</truncated>
		<difficult>0</difficult>
		<bndbox>
			<xmin>189</xmin>
			<ymin>3</ymin>
			<xmax>246</xmax>
			<ymax>178</ymax>
		</bndbox>
	</object>
</annotation>
